{
  "interpretation": [
    "correct_supported=0 means semantic risk was not eliminated.",
    "partially_correct_or_incomplete=2 provides useful but not clean correctness evidence.",
    "unsupported_or_wrong=1 confirms at least one true quality failure.",
    "cannot_determine_from_available_context=3 preserves evidence/reference/proxy uncertainty."
  ],
  "label_counts": {
    "cannot_determine_from_available_context": 3,
    "correct_supported": 0,
    "partially_correct_or_incomplete": 2,
    "unsupported_or_wrong": 1
  },
  "review_complete": true,
  "row_count": 6,
  "source_summary": {
    "human_labels_present": true,
    "human_labels_validated": true,
    "review_sheet_rows": 6
  },
  "status": "HUMAN_REVIEW_EXECUTED",
  "validated_labels_path": "results/phase_2_system_optimization/final_reruns/task103c_r_qmsum_human_review_execution/task103cr_validated_human_labels.jsonl"
}
