{"conditions":[{"condition":"baseline-ar","cpu_compressor_memory_delta_bytes":0,"current_rss_after_compressor_bytes":875245568,"current_rss_before_compressor_bytes":875245568,"model_composition":"target-only GPU","peak_cuda_allocated_bytes":3120494080,"peak_cuda_reserved_bytes":3246391296,"process_peak_rss_bytes":3524526080,"unsupported_resource_fields":["drafter_incremental_gpu_bytes","target_only_gpu_bytes"]},{"condition":"dflash-r1","cpu_compressor_memory_delta_bytes":0,"current_rss_after_compressor_bytes":896163840,"current_rss_before_compressor_bytes":896163840,"model_composition":"target plus drafter GPU","peak_cuda_allocated_bytes":4540579328,"peak_cuda_reserved_bytes":4714397696,"process_peak_rss_bytes":3524427776,"unsupported_resource_fields":["drafter_incremental_gpu_bytes","target_only_gpu_bytes"]},{"condition":"cc-dflash-r2","cpu_compressor_memory_delta_bytes":151887872,"current_rss_after_compressor_bytes":1048084480,"current_rss_before_compressor_bytes":896196608,"model_composition":"target plus drafter GPU; CPU compressor","peak_cuda_allocated_bytes":4185822208,"peak_cuda_reserved_bytes":4267704320,"process_peak_rss_bytes":3524403200,"unsupported_resource_fields":["drafter_incremental_gpu_bytes","target_only_gpu_bytes"]}],"dataset":"qmsum"}
