{
  "claim_policy": "preliminary only; no final speedup, correctness, deployment, or end-to-end benefit claim",
  "comparisons": {
    "CC-DFlash-R2": {
      "after": {
        "avg_answer_token_overlap": 0.228499,
        "avg_compressed_input_tokens": 943.5,
        "avg_compression_ratio": 2.0669195124717197,
        "avg_e2e_latency_s": 7.575937319233344,
        "avg_generation_latency_s": 2.3496063276333796,
        "avg_input_tokens": 1012.1333333333333,
        "avg_original_input_tokens": 1950.4333333333334,
        "avg_output_tokens": 48.666666666666664,
        "avg_t_compress_ms": 5226.330991599965,
        "avg_t_prefill_ms": 361.61656153341636,
        "avg_tau_mean": 2.2919328538950308,
        "avg_tok_per_sec": 20.645862471698617,
        "condition": "CC-DFlash-R2",
        "dataset_names": [
          "qmsum_meeting_qa_long"
        ],
        "e2e_tok_per_sec_weighted": 6.423847586900514,
        "empty_output_count": 0,
        "generated_text_present_count": 30,
        "generation_tok_per_sec_weighted": 20.71268965115775,
        "hit_cap_count": 0,
        "hit_cap_rate": 0.0,
        "low_overlap_count": 15,
        "malformed_output_count": 0,
        "max_new_tokens_values": [
          384
        ],
        "max_vram_allocated_gib": 3.510854721069336,
        "max_vram_reserved_gib": 4.447265625,
        "median_answer_token_overlap": 0.192593,
        "normalized_containment_count": 0,
        "normalized_containment_rate": 0.0,
        "qmsum_concise_policy_preservation_rate": 1.0,
        "qmsum_concise_policy_preserved_count": 30,
        "repetition_count": 0,
        "rows": 30,
        "schema_presence": {
          "R_actual": 30,
          "compressed_input_tokens": 30,
          "condition": 30,
          "dataset_name": 30,
          "expected_answer": 30,
          "fixture_id": 30,
          "generated_text": 30,
          "generation_time_s": 30,
          "keep_rate": 30,
          "max_new_tokens": 30,
          "original_input_tokens": 30,
          "output_tokens": 30,
          "prompt_id": 30,
          "t_compress_ms": 30,
          "t_prefill_ms": 30,
          "tok_per_sec": 30,
          "tokens_per_second": 30
        }
      },
      "avg_e2e_latency_s_delta": -11.479633835366563,
      "avg_output_tokens_delta": -296.66666666666663,
      "avg_overlap_delta": -0.128984,
      "before": {
        "avg_answer_token_overlap": 0.357483,
        "avg_compressed_input_tokens": 943.5,
        "avg_compression_ratio": 2.0669195124717197,
        "avg_e2e_latency_s": 19.055571154599907,
        "avg_generation_latency_s": 13.127243169499918,
        "avg_input_tokens": 979.0333333333333,
        "avg_original_input_tokens": 1950.4333333333334,
        "avg_output_tokens": 345.3333333333333,
        "avg_t_compress_ms": 5928.327985099986,
        "avg_t_prefill_ms": 388.17339046672714,
        "avg_tau_mean": 2.761559017313372,
        "avg_tok_per_sec": 26.504681241798448,
        "condition": "CC-DFlash-R2",
        "dataset_names": [
          "qmsum_meeting_qa_long"
        ],
        "e2e_tok_per_sec_weighted": 18.12243414440883,
        "empty_output_count": 0,
        "generated_text_present_count": 30,
        "generation_tok_per_sec_weighted": 26.306615096129796,
        "hit_cap_count": 21,
        "hit_cap_rate": 0.7,
        "low_overlap_count": 2,
        "malformed_output_count": 0,
        "max_new_tokens_values": [
          384
        ],
        "max_vram_allocated_gib": 3.510854721069336,
        "max_vram_reserved_gib": 4.39453125,
        "median_answer_token_overlap": 0.338095,
        "normalized_containment_count": 0,
        "normalized_containment_rate": 0.0,
        "qmsum_concise_policy_preservation_rate": 0.0,
        "qmsum_concise_policy_preserved_count": 0,
        "repetition_count": 0,
        "rows": 30,
        "schema_presence": {
          "R_actual": 30,
          "compressed_input_tokens": 30,
          "condition": 30,
          "dataset_name": 30,
          "expected_answer": 30,
          "fixture_id": 30,
          "generated_text": 30,
          "generation_time_s": 30,
          "keep_rate": 30,
          "max_new_tokens": 30,
          "original_input_tokens": 30,
          "output_tokens": 30,
          "prompt_id": 30,
          "t_compress_ms": 30,
          "t_prefill_ms": 30,
          "tok_per_sec": 30,
          "tokens_per_second": 30
        }
      },
      "cap_hit_delta": -21,
      "cap_to_noncap_prompt_ids": [
        1,
        5,
        6,
        9,
        10,
        11,
        12,
        13,
        15,
        16,
        17,
        18,
        19,
        21,
        23,
        24,
        26,
        27,
        28,
        29,
        30
      ],
      "condition": "CC-DFlash-R2",
      "noncap_to_cap_prompt_ids": [],
      "policy_preservation_rate": 1.0,
      "proxy_degraded_prompt_ids": [
        1,
        2,
        3,
        4,
        5,
        6,
        7,
        9,
        10,
        12,
        13,
        16,
        18,
        19,
        20,
        21,
        22,
        23,
        24,
        25,
        26,
        29,
        30
      ],
      "proxy_improved_prompt_ids": [
        8
      ],
      "shared_prompt_count": 30
    },
    "LLMLingua-AR-R2": {
      "after": {
        "avg_answer_token_overlap": 0.227541,
        "avg_compressed_input_tokens": 943.5,
        "avg_compression_ratio": 2.0669195124717197,
        "avg_e2e_latency_s": 8.040080427300047,
        "avg_generation_latency_s": 2.8818248496333583,
        "avg_input_tokens": 1012.1333333333333,
        "avg_original_input_tokens": 1950.4333333333334,
        "avg_output_tokens": 48.5,
        "avg_t_compress_ms": 5158.2555776666895,
        "avg_t_prefill_ms": 369.46632790007544,
        "avg_tau_mean": 0.0,
        "avg_tok_per_sec": 16.70700515249886,
        "condition": "LLMLingua-AR-R2",
        "dataset_names": [
          "qmsum_meeting_qa_long"
        ],
        "e2e_tok_per_sec_weighted": 6.032277965195289,
        "empty_output_count": 0,
        "generated_text_present_count": 30,
        "generation_tok_per_sec_weighted": 16.82961405727709,
        "hit_cap_count": 0,
        "hit_cap_rate": 0.0,
        "low_overlap_count": 14,
        "malformed_output_count": 0,
        "max_new_tokens_values": [
          384
        ],
        "max_vram_allocated_gib": 2.5024971961975098,
        "max_vram_reserved_gib": 3.451171875,
        "median_answer_token_overlap": 0.207143,
        "normalized_containment_count": 0,
        "normalized_containment_rate": 0.0,
        "qmsum_concise_policy_preservation_rate": 1.0,
        "qmsum_concise_policy_preserved_count": 30,
        "repetition_count": 0,
        "rows": 30,
        "schema_presence": {
          "R_actual": 30,
          "compressed_input_tokens": 30,
          "condition": 30,
          "dataset_name": 30,
          "expected_answer": 30,
          "fixture_id": 30,
          "generated_text": 30,
          "generation_time_s": 30,
          "keep_rate": 30,
          "max_new_tokens": 30,
          "original_input_tokens": 30,
          "output_tokens": 30,
          "prompt_id": 30,
          "t_compress_ms": 30,
          "t_prefill_ms": 30,
          "tok_per_sec": 30,
          "tokens_per_second": 30
        }
      },
      "avg_e2e_latency_s_delta": -18.338306233233318,
      "avg_output_tokens_delta": -300.03333333333336,
      "avg_overlap_delta": -0.13110300000000003,
      "before": {
        "avg_answer_token_overlap": 0.358644,
        "avg_compressed_input_tokens": 943.5,
        "avg_compression_ratio": 2.0669195124717197,
        "avg_e2e_latency_s": 26.378386660533366,
        "avg_generation_latency_s": 20.80235052063334,
        "avg_input_tokens": 979.0333333333333,
        "avg_original_input_tokens": 1950.4333333333334,
        "avg_output_tokens": 348.53333333333336,
        "avg_t_compress_ms": 5576.036139900028,
        "avg_t_prefill_ms": 375.30881926663824,
        "avg_tau_mean": 0.0,
        "avg_tok_per_sec": 16.76912945991841,
        "condition": "LLMLingua-AR-R2",
        "dataset_names": [
          "qmsum_meeting_qa_long"
        ],
        "e2e_tok_per_sec_weighted": 13.212837381552207,
        "empty_output_count": 0,
        "generated_text_present_count": 30,
        "generation_tok_per_sec_weighted": 16.754516898829856,
        "hit_cap_count": 22,
        "hit_cap_rate": 0.733333,
        "low_overlap_count": 3,
        "malformed_output_count": 0,
        "max_new_tokens_values": [
          384
        ],
        "max_vram_allocated_gib": 2.502498149871826,
        "max_vram_reserved_gib": 3.41796875,
        "median_answer_token_overlap": 0.3379,
        "normalized_containment_count": 0,
        "normalized_containment_rate": 0.0,
        "qmsum_concise_policy_preservation_rate": 0.0,
        "qmsum_concise_policy_preserved_count": 0,
        "repetition_count": 0,
        "rows": 30,
        "schema_presence": {
          "R_actual": 30,
          "compressed_input_tokens": 30,
          "condition": 30,
          "dataset_name": 30,
          "expected_answer": 30,
          "fixture_id": 30,
          "generated_text": 30,
          "generation_time_s": 30,
          "keep_rate": 30,
          "max_new_tokens": 30,
          "original_input_tokens": 30,
          "output_tokens": 30,
          "prompt_id": 30,
          "t_compress_ms": 30,
          "t_prefill_ms": 30,
          "tok_per_sec": 30,
          "tokens_per_second": 30
        }
      },
      "cap_hit_delta": -22,
      "cap_to_noncap_prompt_ids": [
        1,
        4,
        5,
        6,
        9,
        10,
        11,
        12,
        13,
        15,
        16,
        17,
        18,
        19,
        21,
        23,
        24,
        26,
        27,
        28,
        29,
        30
      ],
      "condition": "LLMLingua-AR-R2",
      "noncap_to_cap_prompt_ids": [],
      "policy_preservation_rate": 1.0,
      "proxy_degraded_prompt_ids": [
        1,
        2,
        3,
        4,
        5,
        6,
        7,
        9,
        10,
        12,
        13,
        18,
        19,
        20,
        21,
        22,
        23,
        24,
        25,
        26,
        27,
        29,
        30
      ],
      "proxy_improved_prompt_ids": [
        8
      ],
      "shared_prompt_count": 30
    }
  },
  "decisions": {
    "all_policy_preserved": true,
    "average_overlap_delta": -0.1300435,
    "keep_concise_policy_as_qmsum_default": false,
    "material_proxy_degradation": true,
    "mnt512_still_needed": false,
    "qmsum_n100_justified": false,
    "qmsum_n100_reason": "Still blocked unless explicitly framed as speed-only and quality proxy policy is accepted.",
    "total_after_cap_hits": 0,
    "total_before_cap_hits": 43,
    "total_proxy_degraded": 46,
    "total_proxy_improved": 2
  },
  "status": "PASS_WITH_NOTES",
  "task": "73-qmsum-concise-policy"
}
